{
  "main_title": "Hidden Tunnels of the Underground Railroad Revealed",
  "hook": "[mysterious] What if I told you there were secret tunnels weaving through America? In the 19th century, abolitionists like Harriet Tubman used these hidden passages to guide over 70 enslaved individuals to freedom each trip.",
  "description": "Unearth the hidden tunnels of the Underground Railroad, crucial for freeing enslaved lives! #History #UndergroundRailroad #Abolitionists",
  "tags": [
    "Underground Railroad",
    "Harriet Tubman",
    "Abolitionists"
  ],
  "keywords": [
    "hidden tunnels",
    "freedom",
    "19th century history"
  ],
  "music_category": "Mystery",
  "word_count": 93
}